setup.py
phenom/__init__.py
phenom/__main__.py
phenom/run.py
phenom.egg-info/PKG-INFO
phenom.egg-info/SOURCES.txt
phenom.egg-info/dependency_links.txt
phenom.egg-info/entry_points.txt
phenom.egg-info/requires.txt
phenom.egg-info/top_level.txt